hierarchical_mechanism_LDP/__init__.py
hierarchical_mechanism_LDP/bary_tree.py
hierarchical_mechanism_LDP/computeamplification.py
hierarchical_mechanism_LDP/ldp_protocol.py
hierarchical_mechanism_LDP/mechanism.py
hierarchical_mechanism_LDP/test_functions.py
ldp_hierarchical_mechanism-0.1.3.dist-info/LICENSE
ldp_hierarchical_mechanism-0.1.3.dist-info/METADATA
ldp_hierarchical_mechanism-0.1.3.dist-info/WHEEL
ldp_hierarchical_mechanism-0.1.3.dist-info/top_level.txt
ldp_hierarchical_mechanism-0.1.3.dist-info/RECORD
