Metadata-Version: 2.2
Name: LDP_hierarchical_mechanism
Version: 0.1.3
Summary: Local Differential Privacy for Range Queries
Home-page: https://github.com/NynsenFaber/LDP_hierarchical_mechanism
Author: Fabrizio Boninsegna
Classifier: Development Status :: 4 - Beta
Classifier: Programming Language :: Python :: 3
Classifier: License :: OSI Approved :: MIT License
Classifier: Operating System :: OS Independent
Requires-Python: >=3.6
License-File: LICENSE
Requires-Dist: pure-ldp>=1.2.0
Requires-Dist: scikit-learn==1.6.1
Requires-Dist: statsmodels==0.14.4
Dynamic: author
Dynamic: classifier
Dynamic: description
Dynamic: description-content-type
Dynamic: home-page
Dynamic: requires-dist
Dynamic: requires-python
Dynamic: summary
